{

    "russian": {
		"c": "k",
		"kh": "ch",
		"r": "rr",
		"yes": "da",
		"hello": "privyet",
		"greetings": "privyet",
		"bye": "poka",
		"goodbye": "do svidania",
		"farewell": "do svidania",
		"good": "dobro",
		"evil": "zlo",
		"captain": "kapitan",
		"king": "tsar",
		"queen": "tsaritsa",
		"monarch": "monarkh",
		"monarchy": "monarkhiya",
		"throne": "tron",
		"prince": "prints",
		"princess": "printsessa",
		"templar": "tampliyer",
		"acolyte": "akolit",
		"adventurer": "avantyurist",
		"no": "nyet",
		"fuck": "blyat",
		"heretic": "yeritik",
		"who": "kto",
		"sir": "ser",
		"devil": "dyavol",
		"bridge": "bridzh",
		"bomb": "bomba",
		"garrison": "garnizon",
		"fuck you": "khuy tebe",
		"fuck yourself": "khuy tebe",
		"go fuck yourself": "khuy tebe" // This will do until I get some feedback on it.
		}

}
